rxiv_types/__init__.py
rxiv_types/arxiv.py
rxiv_types/biorxiv.py
rxiv_types/chemrxiv.py
rxiv_types/doaj.py
rxiv_types/medrxiv.py
rxiv_types/models/__init__.py
rxiv_types/models/biorxiv/__init__.py
rxiv_types/models/biorxiv/https/__init__.py
rxiv_types/models/biorxiv/https/api/__init__.py
rxiv_types/models/biorxiv/https/api/biorxiv/__init__.py
rxiv_types/models/biorxiv/https/api/biorxiv/org/__init__.py
rxiv_types/models/biorxiv/https/api/biorxiv/org/oaipmh/__init__.py
rxiv_types/models/biorxiv/https/api/biorxiv/org/oaipmh/bio_rxiv_raw/__init__.py
rxiv_types/models/biorxiv/https/api/biorxiv/org/oaipmh/bio_rxiv_raw/bio_rxiv_raw.py
rxiv_types/models/biorxiv/https/api/biorxiv/org/oaipmh/bio_rxiv_raw/bio_rxiv_raw_type.py
rxiv_types/models/medrxiv/__init__.py
rxiv_types/models/medrxiv/https/__init__.py
rxiv_types/models/medrxiv/https/api/__init__.py
rxiv_types/models/medrxiv/https/api/bio_rxiv/__init__.py
rxiv_types/models/medrxiv/https/api/bio_rxiv/org/__init__.py
rxiv_types/models/medrxiv/https/api/bio_rxiv/org/oaipmh/__init__.py
rxiv_types/models/medrxiv/https/api/bio_rxiv/org/oaipmh/med_rxiv_raw/__init__.py
rxiv_types/models/medrxiv/https/api/bio_rxiv/org/oaipmh/med_rxiv_raw/med_rxiv_raw.py
rxiv_types/models/medrxiv/https/api/bio_rxiv/org/oaipmh/med_rxiv_raw/med_rxiv_raw_type.py
rxiv_types/models/oai_dc/__init__.py
rxiv_types/models/oai_dc/org/__init__.py
rxiv_types/models/oai_dc/org/openarchives/__init__.py
rxiv_types/models/oai_dc/org/openarchives/oai/__init__.py
rxiv_types/models/oai_dc/org/openarchives/oai/pkg_2/__init__.py
rxiv_types/models/oai_dc/org/openarchives/oai/pkg_2/pkg_0/__init__.py
rxiv_types/models/oai_dc/org/openarchives/oai/pkg_2/pkg_0/oai_dc/__init__.py
rxiv_types/models/oai_dc/org/openarchives/oai/pkg_2/pkg_0/oai_dc/dc.py
rxiv_types/models/oai_dc/org/openarchives/oai/pkg_2/pkg_0/oai_dc/oai_dc_type.py
rxiv_types/models/oai_pmh/__init__.py
rxiv_types/models/oai_pmh/org/__init__.py
rxiv_types/models/oai_pmh/org/openarchives/__init__.py
rxiv_types-0.1.0.dist-info/LICENSE
rxiv_types-0.1.0.dist-info/METADATA
rxiv_types-0.1.0.dist-info/WHEEL
rxiv_types-0.1.0.dist-info/RECORD
