Metadata-Version: 2.1
Name: rxiv-types
Version: 0.1.0
Summary: Rxiv XML/JSON parsing and typehints.
Home-page: https://github.com/nicholas-schaub/rxiv-types
License: MIT
Author: Nick Schaub
Author-email: nick.schaub@nih.gov
Requires-Python: >=3.9,<4.0
Classifier: Development Status :: 4 - Beta
Classifier: License :: OSI Approved :: MIT License
Classifier: Operating System :: OS Independent
Classifier: Programming Language :: Python :: 3
Classifier: Programming Language :: Python :: 3.9
Classifier: Programming Language :: Python :: 3.10
Classifier: Programming Language :: Python :: 3.11
Classifier: Programming Language :: Python :: 3.12
Classifier: Topic :: Scientific/Engineering :: Bio-Informatics
Classifier: Topic :: Scientific/Engineering :: Information Analysis
Classifier: Topic :: Scientific/Engineering :: Medical Science Apps.
Classifier: Topic :: Text Processing :: Markup :: XML
Requires-Dist: xsdata-pydantic[cli,lxml,soap] (>=22.10,<23.0)
Project-URL: Issues, https://github.com/nicholas-schaub/rxiv-types/issues
Project-URL: Repository, https://github.com/nicholas-schaub/rxiv-types
